cachecleaner.py
cachecleaner-0.6.dist-info/METADATA
cachecleaner-0.6.dist-info/WHEEL
cachecleaner-0.6.dist-info/entry_points.txt
cachecleaner-0.6.dist-info/top_level.txt
cachecleaner-0.6.dist-info/RECORD
