Metadata-Version: 2.1
Name: cachecleaner
Version: 0.6
Summary: Keeps dir size in given capacity.
Home-page: https://github.com/homm/cachecleaner
Author: Alexander Karpinsky
Author-email: homm86@gmail.com
License: UNKNOWN
Platform: UNKNOWN
Requires-Dist: tqdm (>=4.20.0)
